kaushik_stt/__init__.py
kaushik_speech_to_text-0.3.dist-info/LICENSE.txt
kaushik_speech_to_text-0.3.dist-info/METADATA
kaushik_speech_to_text-0.3.dist-info/WHEEL
kaushik_speech_to_text-0.3.dist-info/top_level.txt
kaushik_speech_to_text-0.3.dist-info/RECORD
