Metadata-Version: 2.1
Name: kaushik-speech-to-text
Version: 0.3
Summary: This code is for speech to text created by me
Author: Kaushik
Author-email: kaushikyadavm857@gmail.com
Classifier: Programming Language :: Python :: 3
Classifier: License :: OSI Approved :: MIT License
Classifier: Operating System :: OS Independent
License-File: LICENSE.txt
